backlight.py
ff_ad5m_backlight-0.1.dist-info/LICENSE
ff_ad5m_backlight-0.1.dist-info/METADATA
ff_ad5m_backlight-0.1.dist-info/WHEEL
ff_ad5m_backlight-0.1.dist-info/entry_points.txt
ff_ad5m_backlight-0.1.dist-info/top_level.txt
ff_ad5m_backlight-0.1.dist-info/RECORD
