Metadata-Version: 2.1
Name: ff-ad5m-backlight
Version: 0.1
Summary: Backlight library for FlashForge Adventurer 5M useing IOCTL.
Author-email: Tristan Timmermans <none@yourbusiness.nowhere>
Maintainer-email: Tristan Timmermans <none@yourbusiness.nowhere>
Keywords: flashforge,adventurer,5m,ad5m,backlight,adm5
Requires-Python: >=3.8
License-File: LICENSE
